ciscodnacbackupctl/__init__.py
ciscodnacbackupctl/cli.py
ciscodnacbackupctl/config.py
ciscodnacbackupctl/debug.py
ciscodnacbackupctl/format.py
ciscodnacbackupctl-0.2.12.dist-info/LICENSE
ciscodnacbackupctl-0.2.12.dist-info/METADATA
ciscodnacbackupctl-0.2.12.dist-info/WHEEL
ciscodnacbackupctl-0.2.12.dist-info/entry_points.txt
ciscodnacbackupctl-0.2.12.dist-info/top_level.txt
ciscodnacbackupctl-0.2.12.dist-info/RECORD
