Metadata-Version: 2.1
Name: ciscodnacbackupctl
Version: 0.2.12
Summary: Cisco DNA Center Backup CLI
Home-page: https://github.com/cskoglun/ciscodnacbackupctl
Author: Robert Csapo
Author-email: rcsapo@cisco.com
Requires-Python: >=3.8
License-File: LICENSE
Requires-Dist: setuptools
Requires-Dist: rich
Requires-Dist: tabulate
Requires-Dist: requests
Requires-Dist: hurry.filesize
Requires-Dist: click
Requires-Dist: schedule
Requires-Dist: daemonocle
